nozyio/__init__.py
nozyio/ast_execution.py
nozyio/code_to_graph.py
nozyio/community_packages.json
nozyio/config_utils.py
nozyio/device_management.py
nozyio/file_picker.py
nozyio/job_queue_manager.py
nozyio/node_package.py
nozyio/scan_modules.py
nozyio/scan_modules_ast.py
nozyio/search_codebase.py
nozyio/server.py
nozyio/utils.py
nozyio/websocket_manager.py
nozyio/bin/linux/rg
nozyio/bin/mac/rg
nozyio/bin/windows/rg.exe
nozyio/web/dist/index.html
nozyio/web/dist/vite.svg
nozyio/web/dist/assets/FlowCanvas-D4COrMmn.js
nozyio/web/dist/assets/Stack-2Xb3rVeY.js
nozyio/web/dist/assets/TopMenu-B_0sOma9.js
nozyio/web/dist/assets/TopMenuCodePreviewButton-B6MsSgqQ.js
nozyio/web/dist/assets/TopMenuNodes-DtY7xZ_c.js
nozyio/web/dist/assets/dialog-BbYNcTN7.js
nozyio/web/dist/assets/index-D-ULYqgV.js
nozyio/web/dist/assets/index-nIlKpDnX.css
nozyio/web/dist/assets/react-vendor-4ldeB94U.js
nozyio/web/dist/assets/reactflow-vendor-BDofclgK.js
nozyio-0.1.17.dist-info/METADATA
nozyio-0.1.17.dist-info/WHEEL
nozyio-0.1.17.dist-info/entry_points.txt
nozyio-0.1.17.dist-info/top_level.txt
nozyio-0.1.17.dist-info/RECORD
