Metadata-Version: 2.1
Name: nozyio
Version: 0.1.17
Summary: Node based workflow orchestration UI for python ML/AI computing
Author-email: oozzy <nozyio.hello@gmail.com>
Project-URL: Repository, https://github.com/oozzy77/nozyio
Requires-Python: >=3.9
Requires-Dist: aiohttp
Requires-Dist: astpretty
Requires-Dist: requests
Requires-Dist: pillow
